LICENSE
MANIFEST.in
README.md
setup.cfg
setup.py
mastodon_archive/__init__.py
mastodon_archive/allowlist.py
mastodon_archive/archive.py
mastodon_archive/context.py
mastodon_archive/core.py
mastodon_archive/expire.py
mastodon_archive/fix.py
mastodon_archive/followers.py
mastodon_archive/following.py
mastodon_archive/html.py
mastodon_archive/login.py
mastodon_archive/media.py
mastodon_archive/meow.py
mastodon_archive/mutuals.py
mastodon_archive/replies.py
mastodon_archive/report.py
mastodon_archive/split.py
mastodon_archive/text.py
mastodon_archive.egg-info/PKG-INFO
mastodon_archive.egg-info/SOURCES.txt
mastodon_archive.egg-info/dependency_links.txt
mastodon_archive.egg-info/entry_points.txt
mastodon_archive.egg-info/requires.txt
mastodon_archive.egg-info/top_level.txt