Metadata-Version: 2.1
Name: mastodon-archive
Version: 1.4.8
Summary: Utility for backing up your Mastodon content
Home-page: https://github.com/kensanata/mastodon-archive#mastodon-archive
Author: Alex Schroeder
Author-email: alex@gnu.org
Classifier: License :: OSI Approved :: GNU General Public License v3 or later (GPLv3+)
Classifier: Programming Language :: Python :: 3 :: Only
Classifier: Topic :: Communications
Classifier: Intended Audience :: End Users/Desktop
Classifier: Environment :: Console
Classifier: Development Status :: 5 - Production/Stable
License-File: LICENSE
